binni6/__init__.py
binni6-0.0.1.dist-info/LICENSE
binni6-0.0.1.dist-info/METADATA
binni6-0.0.1.dist-info/WHEEL
binni6-0.0.1.dist-info/top_level.txt
binni6-0.0.1.dist-info/RECORD
